GPUtil/GPUtil.py
GPUtil/__init__.py
GPUtil/demo_GPUtil.py
GPUtil_fix-1.4.2.dist-info/LICENSE.txt
GPUtil_fix-1.4.2.dist-info/METADATA
GPUtil_fix-1.4.2.dist-info/WHEEL
GPUtil_fix-1.4.2.dist-info/top_level.txt
GPUtil_fix-1.4.2.dist-info/RECORD
