Metadata-Version: 2.1
Name: GPUtil-fix
Version: 1.4.2
Summary: Utility to get the GPU status from NVIDA GPUs using nvidia-smi
Home-page: https://github.com/atarwn/GPUtil-fix
Author: Anders Krogh Mortensen
Author-email: anderskroghm@gmail.com
Maintainer: atarwn
Maintainer-email: a@qwa.su
Classifier: Programming Language :: Python :: 3
Classifier: Programming Language :: Python :: 3.12
License-File: LICENSE.txt
